drip/__init__.py
drip/admin.py
drip/drips.py
drip/exceptions.py
drip/helpers.py
drip/models.py
drip/tasks.py
drip/tokens.py
drip/types.py
drip/urls.py
drip/utils.py
drip/views.py
drip/campaigns/__init__.py
drip/campaigns/admin.py
drip/campaigns/models.py
drip/management/__init__.py
drip/management/commands/__init__.py
drip/management/commands/send_drips.py
drip/migrations/0001_initial.py
drip/migrations/0002_querysetrule_rule_type.py
drip/migrations/0003_testuseruuidmodel.py
drip/migrations/0004_auto_20220713_1317.py
drip/migrations/0005_alter_querysetrule_lookup_type.py
drip/migrations/0006_drip_can_resend_drip.py
drip/migrations/0007_alter_drip_can_resend_drip.py
drip/migrations/0008_auto_20220805_1114.py
drip/migrations/0009_auto_20220809_0806.py
drip/migrations/0010_userunsubscribe.py
drip/migrations/__init__.py
drip/scheduler/__init__.py
drip/scheduler/constants.py
drip/scheduler/cron_scheduler.py
drip/templates/unsubscribe_campaign.html
drip/templates/unsubscribe_campaign_invalid.html
drip/templates/unsubscribe_campaign_success.html
drip/templates/unsubscribe_drip.html
drip/templates/unsubscribe_drip_invalid.html
drip/templates/unsubscribe_drip_success.html
drip/templates/unsubscribe_general.html
drip/templates/unsubscribe_general_invalid.html
drip/templates/unsubscribe_general_success.html
drip/templates/admin/drip/change_form.html
drip/templates/admin/drip/Campaign/change_form.html
drip/templates/admin/drip/SentDrip/change_form.html
drip/templates/campaign/timeline.html
drip/templates/drip/timeline.html
drip/tests/__init__.py
drip/tests/factories.py
drip/tests/test_campaigns.py
drip/tests/test_custom_messages.py
drip/tests/test_drips.py
drip/tests/test_rules.py
drip/tests/test_views.py
django_drip_campaigns-1.16.2.dist-info/AUTHORS.md
django_drip_campaigns-1.16.2.dist-info/LICENSE
django_drip_campaigns-1.16.2.dist-info/METADATA
django_drip_campaigns-1.16.2.dist-info/WHEEL
django_drip_campaigns-1.16.2.dist-info/top_level.txt
django_drip_campaigns-1.16.2.dist-info/RECORD
