Metadata-Version: 2.1
Name: django-drip-campaigns
Version: 1.16.2
Summary: Drip campaigns for Django.
Home-page: https://github.com/rootstrap/django-drip-campaigns
Author: Kalil de Lima
Author-email: kalil@rootstrap.com
License: MIT
Keywords: django drip email user query
Classifier: Development Status :: 4 - Beta
Classifier: Environment :: Web Environment
Classifier: Framework :: Django
Classifier: Intended Audience :: Developers
Classifier: License :: OSI Approved :: MIT License
Classifier: Operating System :: OS Independent
Classifier: Programming Language :: Python
Classifier: Programming Language :: Python :: 3
Classifier: Programming Language :: Python :: 3.4
Classifier: Programming Language :: Python :: 3.5
Classifier: Programming Language :: Python :: 3.6
Classifier: Programming Language :: Python :: 3.7
Classifier: Programming Language :: Python :: Implementation :: CPython
Classifier: Programming Language :: Python :: Implementation :: PyPy
Classifier: Topic :: Software Development :: Libraries :: Python Modules
License-File: LICENSE
License-File: AUTHORS.md
Requires-Dist: Django (>=2.2)
Requires-Dist: apscheduler
Requires-Dist: celery (>=5.2.2)
